{
    "twisted": "ported",
    "twisted._threads": "ported",
    "twisted._threads._convenience": "ported",
    "twisted._threads._ithreads": "ported",
    "twisted._threads._memory": "ported",
    "twisted._threads._pool": "ported",
    "twisted._threads._team": "ported",
    "twisted._threads._threadworker": "ported",
    "twisted._threads.test": "ported",
    "twisted._version": "ported",
    "twisted.application": "ported",
    "twisted.application.app": "ported",
    "twisted.application.internet": "ported",
    "twisted.application.reactors": "ported",
    "twisted.application.service": "ported",
    "twisted.application.strports": "ported",
    "twisted.application.test": "ported",
    "twisted.conch": "ported",
    "twisted.conch.checkers": "ported",
    "twisted.conch.error": "ported",
    "twisted.conch.ssh": "ported",
    "twisted.conch.ssh._cryptography_backports": "ported",
    "twisted.conch.ssh.address": "ported",
    "twisted.conch.ssh.common": "ported",
    "twisted.conch.ssh.keys": "ported",
    "twisted.conch.ssh.sexpy": "ported",
    "twisted.conch.telnet": "ported",
    "twisted.conch.test": "ported",
    "twisted.copyright": "ported",
    "twisted.cred": "ported",
    "twisted.cred._digest": "ported",
    "twisted.cred.checkers": "ported",
    "twisted.cred.credentials": "ported",
    "twisted.cred.error": "ported",
    "twisted.cred.portal": "ported",
    "twisted.cred.strcred": "ported",
    "twisted.cred.test": "ported",
    "twisted.enterprise": "ported",
    "twisted.enterprise.adbapi": "ported",
    "twisted.internet": "ported",
    "twisted.internet._baseprocess": "ported",
    "twisted.internet._glibbase": "ported",
    "twisted.internet._newtls": "ported",
    "twisted.internet._posixserialport": "ported",
    "twisted.internet._posixstdio": "ported",
    "twisted.internet._signals": "ported",
    "twisted.internet._sslverify": "almost-ported",
    "twisted.internet._win32serialport": "ported",
    "twisted.internet.abstract": "ported",
    "twisted.internet.address": "ported",
    "twisted.internet.base": "ported",
    "twisted.internet.default": "ported",
    "twisted.internet.defer": "ported",
    "twisted.internet.endpoints": "ported",
    "twisted.internet.epollreactor": "ported",
    "twisted.internet.error": "ported",
    "twisted.internet.fdesc": "ported",
    "twisted.internet.gireactor": "ported",
    "twisted.internet.gtk3reactor": "ported",
    "twisted.internet.interfaces": "ported",
    "twisted.internet.kqreactor": "ported",
    "twisted.internet.main": "ported",
    "twisted.internet.pollreactor": "ported",
    "twisted.internet.posixbase": "ported",
    "twisted.internet.process": "ported",
    "twisted.internet.protocol": "ported",
    "twisted.internet.reactor": "ported",
    "twisted.internet.selectreactor": "ported",
    "twisted.internet.serialport": "ported",
    "twisted.internet.ssl": "ported",
    "twisted.internet.stdio": "ported",
    "twisted.internet.task": "ported",
    "twisted.internet.tcp": "ported",
    "twisted.internet.test": "ported",
    "twisted.internet.test._posixifaces": "ported",
    "twisted.internet.test.connectionmixins": "ported",
    "twisted.internet.test.fakeendpoint": "ported",
    "twisted.internet.test.modulehelpers": "ported",
    "twisted.internet.test.reactormixins": "ported",
    "twisted.internet.threads": "ported",
    "twisted.internet.udp": "ported",
    "twisted.internet.unix": "ported",
    "twisted.internet.utils": "ported",
    "twisted.logger": "ported",
    "twisted.logger._buffer": "ported",
    "twisted.logger._file": "ported",
    "twisted.logger._filter": "ported",
    "twisted.logger._flatten": "ported",
    "twisted.logger._format": "ported",
    "twisted.logger._global": "ported",
    "twisted.logger._io": "ported",
    "twisted.logger._json": "ported",
    "twisted.logger._legacy": "ported",
    "twisted.logger._levels": "ported",
    "twisted.logger._logger": "ported",
    "twisted.logger._observer": "ported",
    "twisted.logger._stdlib": "ported",
    "twisted.logger._util": "ported",
    "twisted.logger.test": "ported",
    "twisted.names": "ported",
    "twisted.names._rfc1982": "ported",
    "twisted.names.authority": "ported",
    "twisted.names.cache": "ported",
    "twisted.names.client": "ported",
    "twisted.names.common": "ported",
    "twisted.names.dns": "ported",
    "twisted.names.error": "ported",
    "twisted.names.hosts": "ported",
    "twisted.names.resolve": "ported",
    "twisted.names.root": "almost-ported",
    "twisted.names.secondary": "ported",
    "twisted.names.server": "ported",
    "twisted.names.srvconnect": "ported",
    "twisted.names.tap": "ported",
    "twisted.names.test": "ported",
    "twisted.pair": "ported",
    "twisted.pair.raw": "ported",
    "twisted.pair.rawudp": "ported",
    "twisted.pair.test": "ported",
    "twisted.persisted": "ported",
    "twisted.persisted.aot": "ported",
    "twisted.persisted.crefutil": "ported",
    "twisted.persisted.sob": "ported",
    "twisted.persisted.styles": "ported",
    "twisted.persisted.test": "ported",
    "twisted.plugin": "ported",
    "twisted.plugins": "ported",
    "twisted.plugins.cred_anonymous": "ported",
    "twisted.plugins.cred_file": "ported",
    "twisted.plugins.cred_memory": "ported",
    "twisted.plugins.cred_sshkeys": "ported",
    "twisted.plugins.cred_unix": "ported",
    "twisted.plugins.twisted_core": "ported",
    "twisted.plugins.twisted_reactors": "ported",
    "twisted.plugins.twisted_trial": "ported",
    "twisted.plugins.twisted_web": "ported",
    "twisted.positioning": "ported",
    "twisted.positioning._sentence": "ported",
    "twisted.positioning.base": "ported",
    "twisted.positioning.ipositioning": "ported",
    "twisted.positioning.nmea": "ported",
    "twisted.positioning.test": "ported",
    "twisted.protocols": "ported",
    "twisted.protocols.amp": "ported",
    "twisted.protocols.basic": "ported",
    "twisted.protocols.haproxy": "ported",
    "twisted.protocols.haproxy._exceptions": "ported",
    "twisted.protocols.haproxy._info": "ported",
    "twisted.protocols.haproxy._interfaces": "ported",
    "twisted.protocols.haproxy._parser": "ported",
    "twisted.protocols.haproxy._v1parser": "ported",
    "twisted.protocols.haproxy._v2parser": "ported",
    "twisted.protocols.haproxy._wrapper": "ported",
    "twisted.protocols.haproxy.test": "ported",
    "twisted.protocols.haproxy.test.test_parser": "ported",
    "twisted.protocols.haproxy.test.test_v1parser": "ported",
    "twisted.protocols.haproxy.test.test_v2parser": "ported",
    "twisted.protocols.haproxy.test.test_wrapper": "ported",
    "twisted.protocols.loopback": "almost-ported",
    "twisted.protocols.policies": "ported",
    "twisted.protocols.telnet": "ported",
    "twisted.protocols.test": "ported",
    "twisted.protocols.tls": "ported",
    "twisted.protocols.wire": "almost-ported",
    "twisted.python": "ported",
    "twisted.python._appdirs": "ported",
    "twisted.python._oldstyle": "ported",
    "twisted.python._textattributes": "ported",
    "twisted.python._tzhelper": "ported",
    "twisted.python._url": "ported",
    "twisted.python.compat": "ported",
    "twisted.python.components": "ported",
    "twisted.python.constants": "ported",
    "twisted.python.context": "ported",
    "twisted.python.deprecate": "ported",
    "twisted.python.dist": "ported",
    "twisted.python.dist3": "ported",
    "twisted.python.failure": "ported",
    "twisted.python.fakepwd": "ported",
    "twisted.python.filepath": "ported",
    "twisted.python.lockfile": "ported",
    "twisted.python.log": "ported",
    "twisted.python.logfile": "almost-ported",
    "twisted.python.modules": "ported",
    "twisted.python.monkey": "ported",
    "twisted.python.procutils": "ported",
    "twisted.python.randbytes": "ported",
    "twisted.python.reflect": "ported",
    "twisted.python.roots": "ported",
    "twisted.python.runtime": "ported",
    "twisted.python.sendmsg": "ported",
    "twisted.python.syslog": "ported",
    "twisted.python.systemd": "ported",
    "twisted.python.test": "ported",
    "twisted.python.test.deprecatedattributes": "ported",
    "twisted.python.test.modules_helpers": "ported",
    "twisted.python.threadable": "ported",
    "twisted.python.threadpool": "ported",
    "twisted.python.url": "ported",
    "twisted.python.urlpath": "ported",
    "twisted.python.usage": "ported",
    "twisted.python.util": "ported",
    "twisted.python.versions": "ported",
    "twisted.python.win32": "almost-ported",
    "twisted.python.zippath": "ported",
    "twisted.scripts": "ported",
    "twisted.scripts._twistd_unix": "ported",
    "twisted.scripts.trial": "ported",
    "twisted.scripts.twistd": "ported",
    "twisted.test": "ported",
    "twisted.test.iosim": "ported",
    "twisted.test.proto_helpers": "ported",
    "twisted.test.reflect_helper_IE": "almost-ported",
    "twisted.test.reflect_helper_VE": "almost-ported",
    "twisted.test.reflect_helper_ZDE": "almost-ported",
    "twisted.test.ssl_helpers": "ported",
    "twisted.trial": "ported",
    "twisted.trial._asyncrunner": "ported",
    "twisted.trial._asynctest": "ported",
    "twisted.trial._synctest": "ported",
    "twisted.trial.itrial": "ported",
    "twisted.trial.reporter": "ported",
    "twisted.trial.runner": "ported",
    "twisted.trial.test": "ported",
    "twisted.trial.test.detests": "ported",
    "twisted.trial.test.erroneous": "ported",
    "twisted.trial.test.packages": "ported",
    "twisted.trial.test.skipping": "ported",
    "twisted.trial.test.suppression": "ported",
    "twisted.trial.unittest": "ported",
    "twisted.trial.util": "ported",
    "twisted.web": "ported",
    "twisted.web._auth": "ported",
    "twisted.web._auth.basic": "ported",
    "twisted.web._auth.digest": "ported",
    "twisted.web._auth.wrapper": "ported",
    "twisted.web._element": "ported",
    "twisted.web._flatten": "ported",
    "twisted.web._http2": "ported",
    "twisted.web._newclient": "ported",
    "twisted.web._responses": "ported",
    "twisted.web._stan": "ported",
    "twisted.web.client": "almost-ported",
    "twisted.web.demo": "ported",
    "twisted.web.error": "ported",
    "twisted.web.guard": "ported",
    "twisted.web.html": "almost-ported",
    "twisted.web.http": "almost-ported",
    "twisted.web.http_headers": "ported",
    "twisted.web.iweb": "almost-ported",
    "twisted.web.proxy": "ported",
    "twisted.web.resource": "ported",
    "twisted.web.script": "ported",
    "twisted.web.server": "almost-ported",
    "twisted.web.static": "ported",
    "twisted.web.tap": "ported",
    "twisted.web.template": "ported",
    "twisted.web.test": "ported",
    "twisted.web.test.requesthelper": "ported",
    "twisted.web.util": "ported",
    "twisted.web.vhost": "ported",
    "twisted.web.wsgi": "ported",
    "twisted.web.xmlrpc": "ported",
    "twisted.words.protocols.jabber.client": "ported",
    "twisted.words.protocols.jabber.component": "ported",
    "twisted.words.protocols.jabber.error": "ported",
    "twisted.words.protocols.jabber.jid": "ported",
    "twisted.words.protocols.jabber.jstrports": "ported",
    "twisted.words.protocols.jabber.sasl": "ported",
    "twisted.words.protocols.jabber.sasl_mechanisms": "ported",
    "twisted.words.protocols.jabber.xmlstream": "ported",
    "twisted.words.protocols.jabber.xmpp_stringprep": "ported",
    "twisted.words.xish.domish": "ported",
    "twisted.words.xish.utility": "ported",
    "twisted.words.xish.xmlstream": "ported",
    "twisted.words.xish.xpath": "ported",
    "twisted.words.xish.xpathparser": "ported"
}
